[{"country": "Aleppo", "deaths": "3348", "infections": "49942", "death_rate": "6.7"},{"country": "Colombia", "deaths": "430", "infections": "11783", "death_rate": "3.65"},{"country": "Iran", "deaths": "332", "infections": "10783", "death_rate": "3.08"},{"country": "Karachi", "deaths": "6224", "infections": "58101", "death_rate": "10.71"},{"country": "Lebanon", "deaths": "249", "infections": "10167", "death_rate": "2.45"},{"country": "Nairobi", "deaths": "1898", "infections": "20971", "death_rate": "9.05"},{"country": "SaudiArabia", "deaths": "640", "infections": "29815", "death_rate": "2.15"},{"country": "Thailand", "deaths": "3", "infections": "1441", "death_rate": "0.21"},{"country": "Turkey", "deaths": "3", "infections": "4759", "death_rate": "0.06"},{"country": "Venezuela", "deaths": "110", "infections": "3629", "death_rate": "3.03"},{"country": "Yemen", "deaths": "293", "infections": "6659", "death_rate": "4.4"}]