[{"country": "Aleppo", "deaths": "16", "infections": "32322", "death_rate": "0.05"},{"country": "Colombia", "deaths": "4", "infections": "5220", "death_rate": "0.08"},{"country": "Iran", "deaths": "0", "infections": "7277", "death_rate": "0"},{"country": "Karachi", "deaths": "39", "infections": "75671", "death_rate": "0.05"},{"country": "Lebanon", "deaths": "3", "infections": "13001", "death_rate": "0.02"},{"country": "Nairobi", "deaths": "2", "infections": "9985", "death_rate": "0.02"},{"country": "SaudiArabia", "deaths": "6", "infections": "13519", "death_rate": "0.04"},{"country": "Thailand", "deaths": "0", "infections": "0", "death_rate": "0"},{"country": "Turkey", "deaths": "1", "infections": "2886", "death_rate": "0.03"},{"country": "Venezuela", "deaths": "1", "infections": "0", "death_rate": "0"},{"country": "Yemen", "deaths": "0", "infections": "2394", "death_rate": "0"}]